CryptoZero-0.1.0a2.dist-info/LICENSE.txt
CryptoZero-0.1.0a2.dist-info/METADATA
CryptoZero-0.1.0a2.dist-info/RECORD
CryptoZero-0.1.0a2.dist-info/WHEEL
CryptoZero-0.1.0a2.dist-info/top_level.txt
CryptoZero-0.1.0a2.dist-info/zip-safe
cryptozero/__init__.py
cryptozero/key.py
cryptozero/secrecy/__init__.py
cryptozero/secrecy/asymmetric.py
cryptozero/secrecy/symmetric.py
test/__init__.py
test/conftest.py
test/test_key_stretch.py
test/fixtures/__init__.py
test/secrecy/__init__.py
test/secrecy/asymmetric/__init__.py
test/secrecy/asymmetric/decrypt/__init__.py
test/secrecy/asymmetric/decrypt/test_load.py
test/secrecy/asymmetric/encrypt/__init__.py
test/secrecy/asymmetric/encrypt/test_load.py
test/secrecy/symmetric/__init__.py
test/secrecy/symmetric/test_backend_serialisation.py
test/secrecy/symmetric/decrypt/__init__.py
test/secrecy/symmetric/decrypt/test_decryption.py
test/secrecy/symmetric/decrypt/test_get_decrypt_backend.py
test/secrecy/symmetric/decrypt/test_load.py
test/secrecy/symmetric/encrypt/__init__.py
test/secrecy/symmetric/encrypt/test_encryption.py
test/secrecy/symmetric/encrypt/test_load.py
